sanic_service_utils/__init__.py
sanic_service_utils/command.py
sanic_service_utils/common.py
sanic_service_utils/configuration.py
sanic_service_utils/orm_utils.py
sanic_service_utils/tokens.py
tests/__init__.py
tests/orm_utils_test.py
sanic_service_utils-0.6.3.dist-info/LICENSE.txt
sanic_service_utils-0.6.3.dist-info/METADATA
sanic_service_utils-0.6.3.dist-info/WHEEL
sanic_service_utils-0.6.3.dist-info/top_level.txt
sanic_service_utils-0.6.3.dist-info/RECORD
