Metadata-Version: 2.1
Name: sanic-service-utils
Version: 0.6.3
Summary: Toolkit for sanic usage
Home-page: https://gitlab.com/SirEdvin/sanic-service-utils
Author: Bogdan Gladyshev
Author-email: siredvin.dark@gmail.com
License: MIT license
Keywords: sanic rethinkdb
Platform: UNKNOWN
Classifier: Development Status :: 5 - Production/Stable
Classifier: Intended Audience :: Developers
Classifier: License :: OSI Approved :: MIT License
Classifier: Natural Language :: English
Classifier: Programming Language :: Python :: 3.6
Requires-Dist: sanic (>=0.8.0)
Provides-Extra: aiohttp
Requires-Dist: aiohttp (>=2.3.6) ; extra == 'aiohttp'
Provides-Extra: all
Requires-Dist: sanic-jinja2 (>=0.5.5) ; extra == 'all'
Requires-Dist: aiohttp (>=2.3.6) ; extra == 'all'
Requires-Dist: sentry-sdk (~=0.6.5) ; extra == 'all'
Requires-Dist: anji-orm (>=0.6.0) ; extra == 'all'
Requires-Dist: sanic-openapi ; extra == 'all'
Requires-Dist: sanic-session ; extra == 'all'
Requires-Dist: sanic-oauth (>=0.1.1) ; extra == 'all'
Requires-Dist: click (~=7.0) ; extra == 'all'
Requires-Dist: ipython (>=7.1.1) ; extra == 'all'
Requires-Dist: dynaconf (!=2.1.0,>=2.0.2) ; extra == 'all'
Requires-Dist: python-json-logger (>=0.1.11) ; extra == 'all'
Requires-Dist: structlog ; extra == 'all'
Provides-Extra: anji_orm
Requires-Dist: anji-orm (>=0.6.0) ; extra == 'anji_orm'
Requires-Dist: sanic-openapi ; extra == 'anji_orm'
Provides-Extra: commands
Requires-Dist: click (~=7.0) ; extra == 'commands'
Requires-Dist: ipython (>=7.1.1) ; extra == 'commands'
Provides-Extra: configuration
Requires-Dist: dynaconf (!=2.1.0,>=2.0.2) ; extra == 'configuration'
Requires-Dist: python-json-logger (>=0.1.11) ; extra == 'configuration'
Requires-Dist: structlog ; extra == 'configuration'
Provides-Extra: jinja2
Requires-Dist: sanic-jinja2 (>=0.5.5) ; extra == 'jinja2'
Provides-Extra: oauth
Requires-Dist: sanic-oauth (>=0.1.1) ; extra == 'oauth'
Provides-Extra: sentry
Requires-Dist: sentry-sdk (~=0.6.5) ; extra == 'sentry'
Provides-Extra: sessions
Requires-Dist: sanic-session ; extra == 'sessions'
